cs_models/__init__.py
cs_models/aact_database/__init__.py
cs_models/database/__init__.py
cs_models/database/operations.py
cs_models/database/test_operations.py
cs_models/graph_database/__init__.py
cs_models/graph_database/operations.py
cs_models/resources/__init__.py
cs_models/resources/all_models.py
cs_models/resources/AbstractText/__init__.py
cs_models/resources/AbstractText/models.py
cs_models/resources/AbstractText/schemas.py
cs_models/resources/AbstractText/test_abstract_text.py
cs_models/resources/ActionLog/__init__.py
cs_models/resources/ActionLog/models.py
cs_models/resources/ActionLog/schemas.py
cs_models/resources/AmountLicensingCollab/__init__.py
cs_models/resources/AmountLicensingCollab/models.py
cs_models/resources/AmountLicensingCollab/schemas.py
cs_models/resources/ArtifactVectorIndex/__init__.py
cs_models/resources/ArtifactVectorIndex/models.py
cs_models/resources/ArtifactVectorIndex/schemas.py
cs_models/resources/ArtifactVectorIndexQueue/__init__.py
cs_models/resources/ArtifactVectorIndexQueue/models.py
cs_models/resources/ArtifactVectorIndexQueue/schemas.py
cs_models/resources/Assignee/__init__.py
cs_models/resources/Assignee/models.py
cs_models/resources/Assignee/schemas.py
cs_models/resources/AssistantCommand/__init__.py
cs_models/resources/AssistantCommand/models.py
cs_models/resources/AssistantCommand/schemas.py
cs_models/resources/AssistantCommandArtifact/__init__.py
cs_models/resources/AssistantCommandArtifact/models.py
cs_models/resources/AssistantCommandArtifact/schemas.py
cs_models/resources/AssistantCommandChart/__init__.py
cs_models/resources/AssistantCommandChart/models.py
cs_models/resources/AssistantCommandChart/schemas.py
cs_models/resources/AssistantCommandEdge/__init__.py
cs_models/resources/AssistantCommandEdge/models.py
cs_models/resources/AssistantCommandTable/__init__.py
cs_models/resources/AssistantCommandTable/models.py
cs_models/resources/AssistantCommandTable/schemas.py
cs_models/resources/AssistantCopilot/__init__.py
cs_models-0.0.864.dist-info/METADATA
cs_models-0.0.864.dist-info/WHEEL
cs_models-0.0.864.dist-info/top_level.txt
cs_models-0.0.864.dist-info/RECORD
