Metadata-Version: 2.1
Name: cs-models
Version: 0.0.864
Summary: MySQL db models
Home-page: https://github.com/mindgram/cs-models
Author: Shrey Verma
Author-email: sverma@mindgram.ai
License: UNKNOWN
Platform: UNKNOWN
Classifier: Programming Language :: Python :: 3
Requires-Python: >=3.8
Requires-Dist: marshmallow==3.19.0
Requires-Dist: PyMySQL==1.1.1
Requires-Dist: python-dateutil==2.8.2
Requires-Dist: pytz==2022.1
Requires-Dist: SQLAlchemy==1.4.35
Requires-Dist: boto3>=1.28.30
Requires-Dist: botocore>=1.31.30
Requires-Dist: s3transfer>=0.6.2
Requires-Dist: six==1.16.0
Requires-Dist: urllib3>=1.26.19
Requires-Dist: dnspython==2.6.1
Requires-Dist: pymongo==4.6.3
Requires-Dist: psycopg2-binary<=2.9.9,>=2.9.3
Requires-Dist: sshtunnel==0.4.0
